<?xml version="1.0" encoding="UTF-8"?>
<root>
    <item>
        <link>admin/</link>
        <name>News</name>
        <icon>newspaper.png</icon>
        <rights>
            <right>ADMIN_ACCESS_DASHBOARD</right>
        </rights>
    </item>
    <item>
        <name>SYSTEM</name>
        <icon>server.png</icon>
        <item>
            <name>USER</name>
            <icon>group.png</icon>
            <link>rights/</link>
            <rights>
                <right>rights_access_dashboard</right>
                <right>admin_delete_user</right>
                <right>admin_edit_user</right>
                <right>admin_create_user</right>
                <right>admin_add_remove_user_to_group</right>
            </rights>
        </item>
        <item>
            <name>MENUE-LINKS</name>
            <icon>bullet_blue.png</icon>
            <link>menue-links/</link>
            <rights>
                <right>EDIT_MENUE_LINK</right>
            </rights>
        </item>
        <item>
            <name>CONFIGURATION</name>
            <icon>cog.png</icon>
            <link>config/</link>
            <rights>
                <right>edit_config</right>
            </rights>
        </item>
        <item>
            <name>UPDATE</name>
            <icon>arrow_refresh.png</icon>
            <link>update/</link>
            <rights>
                <right>run_system_update</right>
            </rights>
        </item>
    </item>
    <item>
        <name>HOME</name>
        <link>index.php</link>
        <icon>house.png</icon>
            <item>
                <name>LOG_OUT</name>
                <link>logout/</link>
                <icon>house_go.png</icon>
            </item>
    </item>
</root>
